flask_odoo/__init__.py
flask_odoo/model.py
flask_odoo/types.py
Flask_Odoo-0.4.2.dist-info/LICENSE.txt
Flask_Odoo-0.4.2.dist-info/METADATA
Flask_Odoo-0.4.2.dist-info/WHEEL
Flask_Odoo-0.4.2.dist-info/top_level.txt
Flask_Odoo-0.4.2.dist-info/RECORD
