Metadata-Version: 2.1
Name: Flask-Odoo
Version: 0.4.2
Summary: Flask-Odoo is an extension for Flask that aims to simplify the integration with the Odoo XML-RPC API
Home-page: https://github.com/teamgeek-io/flask-odoo
Author: Teamgeek
Author-email: support@teamgeek.io
License: MIT
Keywords: utilities,development
Platform: UNKNOWN
Classifier: Development Status :: 3 - Alpha
Classifier: Intended Audience :: Developers
Classifier: Topic :: Software Development :: Libraries
Classifier: License :: OSI Approved :: MIT License
Classifier: Programming Language :: Python :: 3
Requires-Python: >=3.6
